fast_jinjasql/__init__.py
fast_jinjasql/_nbdev.py
fast_jinjasql/core.py
fast_jinjasql-0.0.2.dist-info/LICENSE
fast_jinjasql-0.0.2.dist-info/METADATA
fast_jinjasql-0.0.2.dist-info/WHEEL
fast_jinjasql-0.0.2.dist-info/entry_points.txt
fast_jinjasql-0.0.2.dist-info/top_level.txt
fast_jinjasql-0.0.2.dist-info/RECORD
